[
    {
        "bookName": "Bhagavad Gita: Yatharoop",
        "author": "A.C. Bhaktivedanta Swami Prabhupada",
        "price": "Rs.455",
        "Binding": "Paperback",
        "Release": "01 Nov 2020",
        "Language": "English"
    },
    {
        "bookName": "My First Library: Boxset of 10 Board Books for Kids",
        "author": "Wonder House Books Editorial",
        "price": "Rs.517",
        "Binding": "Paperback",
        "Release": "01 Nov 2020",
        "Language": "English"
    },
    {
        "bookName": "World\u2019s Greatest Books For Personal Growth & Wealth (Set of 4 Books) : Perfect Motivational Gift Set",
        "author": "Dale Carnegie, Napoleon Hill, Dr. Joseph Murphy & George S. Clason",
        "price": "Rs.482",
        "Binding": "Paperback",
        "Release": "01 Nov 2020",
        "Language": "English"
    },
    {
        "bookName": "MTG Objective NCERT at your FINGERTIPS - Biology, Best NEET Books (Based on NCERT Pattern - Latest & Revised Edition 2022)",
        "author": "MTG Editorial Board",
        "price": "Rs.666",
        "Binding": "Paperback",
        "Release": "01 Nov 2020",
        "Language": "English"
    },
    {
        "bookName": "My First 4 In 1 Alphabet Numbers Colours Shapes: Padded Board Books",
        "author": "Wonder House Books",
        "price": "Rs.233",
        "Binding": "Paperback",
        "Release": "01 Nov 2020",
        "Language": "English"
    },
    {
        "bookName": "Fruits - My First Early Learning Wall Chart: For Preschool, Kindergarten, Nursery And Homeschooling (19 Inches X 29 Inches)",
        "author": "Wonder House Books",
        "price": "Rs.105",
        "Binding": "Paperback",
        "Release": "01 Nov 2020",
        "Language": "English"
    },
    {
        "bookName": "Oswaal CBSE Chapterwise & Topicwise Question Bank Class 10 Science Book (For 2022-23 Exam)",
        "author": "Oswaal Editorial Board",
        "price": "Rs.672",
        "Binding": "Paperback",
        "Release": "01 Nov 2020",
        "Language": "English"
    },
    {
        "bookName": "Little Colouring Books for Kids (Set of 10 Books) - Gift to children for painting, drawing and colouring - Alphabets, Animals, Birds, Flags, Flowers, ... Transport, Vegetables - 3 to 6 years old",
        "author": "Maple Press ",
        "price": "Rs.242",
        "Binding": "Paperback",
        "Release": "01 Nov 2020",
        "Language": "English"
    },
    {
        "bookName": "My First Complete Learning Library: Boxset of 20 Board Books Gift Set for Kids (Horizontal Design)",
        "author": "Wonder House Books",
        "price": "Rs.1,019",
        "Binding": "Paperback",
        "Release": "01 Nov 2020",
        "Language": "English"
    },
    {
        "bookName": "Fruits",
        "author": "Pegasus Team",
        "price": "Rs.176",
        "Binding": "Paperback",
        "Release": "01 Nov 2020",
        "Language": "English"
    },
    {
        "bookName": "Skin Disease-Diagnosis & Treatment:First South Asia Edition-E-book",
        "author": "Habif MD, Thomas P.",
        "price": "Rs.2,965",
        "Binding": "Paperback",
        "Release": "01 Nov 2020",
        "Language": "English"
    },
    {
        "bookName": "Ugly Love",
        "author": "Colleen Hoover ",
        "price": "Rs.274",
        "Binding": "Paperback",
        "Release": "01 Nov 2020",
        "Language": "English"
    },
    {
        "bookName": "Brain Games For Clever Kids (R)",
        "author": "Gareth Moore",
        "price": "Rs.219",
        "Binding": "Paperback",
        "Release": "01 Nov 2020",
        "Language": "English"
    },
    {
        "bookName": "Oswaal CBSE Chapterwise & Topicwise Question Bank Class 10 Mathematics Standard Book (For 2022-23 Exam)",
        "author": "Oswaal Editorial Board",
        "price": "Rs.563",
        "Binding": "Paperback",
        "Release": "01 Nov 2020",
        "Language": "English"
    },
    {
        "bookName": "Charts: World of Flags Charts (Educational Charts for kids)",
        "author": "Om Books Editorial Team",
        "price": "Rs.99",
        "Binding": "Paperback",
        "Release": "01 Nov 2020",
        "Language": "English"
    },
    {
        "bookName": "Skeletal System",
        "author": "Pegasus Team",
        "price": "Rs.190",
        "Binding": "Paperback",
        "Release": "01 Nov 2020",
        "Language": "English"
    },
    {
        "bookName": "Oswaal CBSE Chapterwise & Topicwise Question Bank Class 10 Social Science Book (For 2022-23 Exam)",
        "author": "Oswaal Editorial Board",
        "price": "Rs.664",
        "Binding": "Paperback",
        "Release": "01 Nov 2020",
        "Language": "English"
    },
    {
        "bookName": "Writing Practice Boxset: Pack of 4 Books (Writing Fun: Write And Practice Capital Letters, Small Letters, Patterns and Numbers 1 to 10)",
        "author": "Wonder House Books",
        "price": "Rs.295",
        "Binding": "Paperback",
        "Release": "01 Nov 2020",
        "Language": "English"
    },
    {
        "bookName": "Pride & Prejudice",
        "author": "Prakash Books India Pvt. Ltd.",
        "price": "Rs.202",
        "Binding": "Paperback",
        "Release": "01 Nov 2020",
        "Language": "English"
    },
    {
        "bookName": "World\u2019s Best Inspirational Books to Change Your Life (Box Set of 3 Books)",
        "author": "Dale Carnegie, Napoleon Hill, Joseph Murphy",
        "price": "Rs.419",
        "Binding": "Paperback",
        "Release": "01 Nov 2020",
        "Language": "English"
    }
]